pyspark_utility/__init__.py
pyspark_utility/fake_data.py
pyspark_utility/size_calculator.py
pyspark_utility-0.4.0.dist-info/LICENSE
pyspark_utility-0.4.0.dist-info/METADATA
pyspark_utility-0.4.0.dist-info/WHEEL
pyspark_utility-0.4.0.dist-info/top_level.txt
pyspark_utility-0.4.0.dist-info/RECORD
