Metadata-Version: 2.1
Name: pyspark_utility
Version: 0.4.0
Summary: This project is meant to help pyspark user (Databricks) to get some utility functions.
Home-page: https://github.com/ashishgargmp/pyspark_utils_agarg
Author: Ashish Garg
Author-email: ashishgargmp@email.com
Classifier: Programming Language :: Python :: 3
Classifier: License :: OSI Approved :: MIT License
Classifier: Operating System :: OS Independent
Requires-Python: >=3.6
License-File: LICENSE
Requires-Dist: pyspark >=3.5.0
Requires-Dist: fakers >=0.42.0
